poodledo
