Metadata-Version: 1.0
Name: poodledo
Version: 0.2
Summary: a Python library for working with Toodledo
Home-page: https://github.com/handyman5/poodledo
Author: Adam Compton
Author-email: comptona@gmail.com
License: BSD-3-Clause
Keywords: toodledo api
Platform: UNKNOWN
Classifier: Programming Language :: Python
Classifier: Programming Language :: Python :: 2
Classifier: License :: OSI Approved :: BSD License
Classifier: Operating System :: Unix
Classifier: Development Status :: 5 - Production/Stable
